<?xml version="1.0" encoding="UTF-8"?>
<metadata xmlns:dc="http://purl.org/dc/elements/1.1/">
  <dc:title>Audio digitale: breve storia delle DAW e il loro utilizzo</dc:title>
  <dc:creator>Andrea Casati</dc:creator>
  <dc:subject>Audio digitale, DAW</dc:subject>
  <dc:description>Brevi cenni sull'audio digitale, sulle DAW, sulla loro storia e il loro utilizzo, con uno sguardo alle applicazioni future.</dc:description>
  <dc:publisher>Self publishing</dc:publisher>
  <dc:contributor>-</dc:contributor>
  <dc:date>2024-07-16</dc:date>
  <dc:type>Text</dc:type>
  <dc:format>ePub</dc:format>
  <dc:identifier>-</dc:identifier>
  <dc:source>-</dc:source>
  <dc:language>it</dc:language>
  <dc:relation>-</dc:relation>
  <dc:coverage>-</dc:coverage>
  <dc:rights>Creative Commons</dc:rights>
</metadata>
